{
  "title": "How Do Bengal Cats Work?",
  "itunes:title": "How Do Bengal Cats Work?",
  "description": "<p>Bengal cats are a hybrid of domestic cats and a small, wild type of leopard cat. Learn how this breed began and why they're an intensive pet in this episode of BrainStuff.</p><p> </p> Learn more about your ad-choices at <a href=\"https://www.iheartpodcastnetwork.com\">https://www.iheartpodcastnetwork.com</a><p>See <a href=\"https://omnystudio.com/listener\">omnystudio.com/listener</a> for privacy information.</p>",
  "content:encoded": "<p>Bengal cats are a hybrid of domestic cats and a small, wild type of leopard cat. Learn how this breed began and why they're an intensive pet in this episode of BrainStuff.</p><p> </p> Learn more about your ad-choices at <a href=\"https://www.iheartpodcastnetwork.com\">https://www.iheartpodcastnetwork.com</a><p>See <a href=\"https://omnystudio.com/listener\">omnystudio.com/listener</a> for privacy information.</p>",
  "itunes:episodeType": "full",
  "itunes:author": "iHeartPodcasts",
  "itunes:image": "",
  "media:content": [
    {
      "media:player": ""
    },
    ""
  ],
  "guid": "5135e2da-53a1-11e8-9c4d-c381c95a3630",
  "omny:clipId": "607c8fec-6024-4e71-ae94-ae320042f2b7",
  "pubDate": "Fri, 24 Jan 2020 12:18:07 +0000",
  "itunes:duration": 362,
  "enclosure": "",
  "link": "https://omny.fm/shows/brainstuff/how-do-bengal-cats-work"
}