{
  "id": "yt:video:1fy-to1uFCg",
  "yt:videoId": "1fy-to1uFCg",
  "yt:channelId": "UCAYKj_peyESIMDp5LtHlH2A",
  "title": "Speedboat Live",
  "link": "",
  "author": {
    "name": "unfa🇺🇦",
    "uri": "https://www.youtube.com/channel/UCAYKj_peyESIMDp5LtHlH2A"
  },
  "published": "2022-10-25T15:09:52+00:00",
  "updated": "2022-10-30T13:42:10+00:00",
  "media:group": {
    "media:title": "Speedboat Live",
    "media:content": "",
    "media:thumbnail": "",
    "media:description": "",
    "media:community": {
      "media:starRating": "",
      "media:statistics": ""
    }
  }
}