{
  "title": "Episode 2: Giving Back To Those Who Served",
  "itunes:title": "Episode 2: Giving Back To Those Who Served",
  "description": "<p>For the Calabrese family, based in Utica, New York, serving their community is a family tradition. In 2013, John Calabrese Sr. and his wife Lori embarked on a new career by opening up their own Express Employment Professionals franchise. Intrigued by the business, their son, John Jr., joined the cause and began doing the important work of matching candidates with companies and vice versa. Along the way, he noted that a lot of the area's unemployed were also veterans - many of them homeless and struggling. So he and his family launched the Veterans Supply Drive initiative, using two repurposed military vehicles to collect and distribute food and clothing, as well as monetary donations for like-minded charities. Thirty tons of donated food later, John Jr has received awards for his important and proactive work.</p><p> </p> Learn more about your ad-choices at <a href=\"https://www.iheartpodcastnetwork.com\">https://www.iheartpodcastnetwork.com</a><p>See <a href=\"https://omnystudio.com/listener\">omnystudio.com/listener</a> for privacy information.</p>",
  "content:encoded": "<p>For the Calabrese family, based in Utica, New York, serving their community is a family tradition. In 2013, John Calabrese Sr. and his wife Lori embarked on a new career by opening up their own Express Employment Professionals franchise. Intrigued by the business, their son, John Jr., joined the cause and began doing the important work of matching candidates with companies and vice versa. Along the way, he noted that a lot of the area's unemployed were also veterans - many of them homeless and struggling. So he and his family launched the Veterans Supply Drive initiative, using two repurposed military vehicles to collect and distribute food and clothing, as well as monetary donations for like-minded charities. Thirty tons of donated food later, John Jr has received awards for his important and proactive work.</p><p> </p> Learn more about your ad-choices at <a href=\"https://www.iheartpodcastnetwork.com\">https://www.iheartpodcastnetwork.com</a><p>See <a href=\"https://omnystudio.com/listener\">omnystudio.com/listener</a> for privacy information.</p>",
  "itunes:episodeType": "full",
  "itunes:author": "iHeartPodcasts",
  "itunes:image": "",
  "media:content": [
    {
      "media:player": ""
    },
    ""
  ],
  "guid": "3b54bf82-af2d-11eb-9772-4781e245924b",
  "omny:clipId": "bd769bb9-7c07-41be-b4d2-ae28003ef29f",
  "pubDate": "Tue, 11 May 2021 05:00:00 +0000",
  "itunes:duration": 926,
  "enclosure": "",
  "link": "https://omny.fm/shows/the-bobby-bones-show/episode-2-giving-back-to-those-who-served"
}