{
  "guid": "tag:soundcloud,2010:tracks/1325795623",
  "title": "BONUS EPISODE: Tink & Hitmaka On Stepping Away, Mental Health, Songwriting + 'Pillow Talk'",
  "pubDate": "Wed, 17 Aug 2022 13:46:03 +0000",
  "link": "https://soundcloud.com/hot97ny/bonus-episode-tink-hitmaka-on",
  "itunes:duration": "00:29:55",
  "itunes:author": "Ebro In The Morning on HOT 97",
  "itunes:explicit": "yes",
  "itunes:summary": "<p>Singer &amp; Songwriter <strong>Tink </strong>and producer <strong>Hitmaka </strong>sat down with Ebro in the Morning for a great conversation surrounding the topic of mental health, the singer's decision to step away and reset from the music business, the difference between being an artist and a songwriter and much more. </p>\n<p><strong>'Pillow Talk' is set to be released Friday, August 19. </strong></p><p>See <a href=\"https://omnystudio.com/listener\">omnystudio.com/listener</a> for privacy information.</p>",
  "itunes:subtitle": "<p>Singer &amp; Songwriter <strong>Tink </strong>…",
  "description": "<p>Singer &amp; Songwriter <strong>Tink </strong>and producer <strong>Hitmaka </strong>sat down with Ebro in the Morning for a great conversation surrounding the topic of mental health, the singer's decision to step away and reset from the music business, the difference between being an artist and a songwriter and much more. </p>\n<p><strong>'Pillow Talk' is set to be released Friday, August 19. </strong></p><p>See <a href=\"https://omnystudio.com/listener\">omnystudio.com/listener</a> for privacy information.</p>",
  "enclosure": "",
  "itunes:image": ""
}