{
  "guid": "s02-e07",
  "title": "S02 Episode 07: Hindsight, Part 1",
  "description": "<p>It makes sense if you’re Bowe Bergdahl.<img src=\"http://feeds.feedburner.com/~r/serialpodcast/~4/xFiGWl0XK1Y\" height=\"1\" width=\"1\" alt=\"\" /></p>\n",
  "pubDate": "Thu, 18 Feb 2016 10:30:00 +0000",
  "author": "rich@thislife.org (This American Life)",
  "link": "https://serialpodcast.org/season-two/7/hindsight-part-1",
  "content:encoded": "<p>It makes sense if you’re Bowe Bergdahl.<img src=\"http://feeds.feedburner.com/~r/serialpodcast/~4/xFiGWl0XK1Y\" height=\"1\" width=\"1\" alt=\"\" /></p>\n",
  "enclosure": "",
  "itunes:title": "S02 Episode 07: Hindsight, Part 1",
  "itunes:author": "This American Life",
  "itunes:duration": "00:36:50",
  "itunes:summary": "It makes sense if you’re Bowe Bergdahl.",
  "itunes:subtitle": "It makes sense if you’re Bowe Bergdahl.",
  "itunes:explicit": "yes",
  "itunes:episodeType": "full"
}