{
  "guid": "tag:soundcloud,2010:tracks/256073876",
  "title": "309 The Power of Meditation with Andy Puddicombe",
  "description": "<p>\"Meditation is at its best when we use it for prevention.\" - Andy Puddicombe<br />\nIf you enjoyed this episode, check out show notes, video and more at http://lewishowes.com/309</p>\n",
  "pubDate": "Wed, 30 Mar 2016 06:32:14 +0000",
  "author": "podcast@schoolofgreatness.com (Lewis Howes)",
  "link": "http://lewishowes.com",
  "content:encoded": "<p>\"Meditation is at its best when we use it for prevention.\" - Andy Puddicombe<br />\nIf you enjoyed this episode, check out show notes, video and more at http://lewishowes.com/309</p>\n",
  "enclosure": "",
  "itunes:title": "309 The Power of Meditation with Andy Puddicombe",
  "itunes:author": "Lewis Howes",
  "itunes:image": "",
  "itunes:duration": "01:16:58",
  "itunes:summary": "\"Meditation is at its best when we use it for prevention.\" - Andy Puddicombe\nIf you enjoyed this episode, check out show notes, video and more at http://lewishowes.com/309",
  "itunes:subtitle": "\"Meditation is at its best when we use it for prevention.\" - Andy Puddicombe\nIf you enjoyed this episode, check out show notes, video and more at http://lewishowes.com/309",
  "itunes:keywords": "inspiration, health, mindfulness, meditation, habits, mental health",
  "itunes:explicit": "no",
  "itunes:episodeType": "full"
}