{
  "id": "yt:video:kaoS47URiPg",
  "yt:videoId": "kaoS47URiPg",
  "yt:channelId": "UCjsEa56tH23ogoXjZsNQ1CA",
  "title": "Submechanophobia",
  "link": "",
  "author": {
    "name": "CreepyDemon",
    "uri": "https://www.youtube.com/channel/UCjsEa56tH23ogoXjZsNQ1CA"
  },
  "published": "2021-04-24T18:50:07+00:00",
  "updated": "2022-06-06T01:07:31+00:00",
  "media:group": {
    "media:title": "Submechanophobia",
    "media:content": "",
    "media:thumbnail": "",
    "media:description": "Hey everyone, here is a short video I made about submechanophobia. Please consider subscribing if you enjoy my content. \n\nSubscribe here ►  https://www.youtube.com/channel/UCjsEa56tH23ogoXjZsNQ1CA?sub_conformation=1   \nDiscord ►  https://discord.gg/HF5DTQkzFg\nTwitter ►  https://twitter.com/DemonCreepy \nReddit - r/submechanophobia ► https://www.reddit.com/r/submechanophobia/\nReddit ►   https://www.reddit.com/user/CreepyDemon\nEmail ►  demoncreepyYT@gmail.com\nWatch another video here ► https://youtu.be/KZUgVW1DkVA\n\n-Sources-\nhttps://www.youtube.com/watch?v=xnnDu_PGFBc&list=PLvGkNvFh-ega6g0Soz5rgTA_8ap1F4wM1&index=1 - Submechanophobia: A large propeller emerges from the gloom.\nhttps://www.youtube.com/watch?v=cDownek0GD8&list=PLvGkNvFh-ega6g0Soz5rgTA_8ap1F4wM1&index=2 - Navy mine?? Panama City Beach, Florida\nhttps://www.youtube.com/watch?v=ZzbGjJwJe80&list=PLvGkNvFh-ega6g0Soz5rgTA_8ap1F4wM1&index=4 - Sonar Sounds",
    "media:community": {
      "media:starRating": "",
      "media:statistics": ""
    }
  }
}