{
  "title": "Fire in the Maternity Ward Special Extravaganza",
  "itunes:title": "Fire in the Maternity Ward Special Extravaganza",
  "description": "The build up to Anthony's new comedy special that has been widely anticipated is finally here. Gregg brings in some friends to wish Anthony congrats and Ellis, Anthony's goddaughter, makes an appearance.<br>Learn more about your ad choices. Visit megaphone.fm/adchoices",
  "content:encoded": "The build up to Anthony's new comedy special that has been widely anticipated is finally here. Gregg brings in some friends to wish Anthony congrats and Ellis, Anthony's goddaughter, makes an appearance.<br>Learn more about your ad choices. Visit megaphone.fm/adchoices",
  "category": [
    "jeselnik & rosenthal vanity project",
    "Anthony Jeselnik",
    "GREGG ROSENTHAL",
    "All Things Comedy",
    "Comedy",
    "podcast"
  ],
  "itunes:keywords": "jeselnik & rosenthal vanity project, Anthony Jeselnik, GREGG ROSENTHAL, All Things Comedy, Comedy, podcast",
  "itunes:episodeType": "full",
  "itunes:author": "All Things Comedy",
  "itunes:image": "",
  "media:content": [
    {
      "media:player": ""
    },
    ""
  ],
  "guid": "gid://art19-episode-locator/V0/5lgCledIz2mQ-X8A-KlMv-Y3xVCFH-MJD8GC05CAIAk",
  "omny:clipId": "7612c3ef-d2a0-469e-8731-aca8005f090f",
  "pubDate": "Wed, 01 May 2019 03:10:23 +0000",
  "itunes:duration": 2654,
  "enclosure": "",
  "link": "https://omny.fm/shows/the-jeselnik-rosenthal-vanity-project/fire-in-the-maternity-ward-special-extravaganza",
  "itunes:explicit": "yes"
}