{
  "title": "How Many Legs Do Millipedes Have?",
  "itunes:title": "How Many Legs Do Millipedes Have?",
  "description": "<p>Millipedes don't literally have a thousand legs, but how many do they really have? Learn about these fascinating arthropods in this episode of BrainStuff.</p><p> </p> Learn more about your ad-choices at <a href=\"https://www.iheartpodcastnetwork.com\">https://www.iheartpodcastnetwork.com</a><p>See <a href=\"https://omnystudio.com/listener\">omnystudio.com/listener</a> for privacy information.</p>",
  "content:encoded": "<p>Millipedes don't literally have a thousand legs, but how many do they really have? Learn about these fascinating arthropods in this episode of BrainStuff.</p><p> </p> Learn more about your ad-choices at <a href=\"https://www.iheartpodcastnetwork.com\">https://www.iheartpodcastnetwork.com</a><p>See <a href=\"https://omnystudio.com/listener\">omnystudio.com/listener</a> for privacy information.</p>",
  "itunes:episodeType": "full",
  "itunes:author": "iHeartPodcasts",
  "itunes:image": "",
  "media:content": [
    {
      "media:player": ""
    },
    ""
  ],
  "guid": "5b9b55de-539c-11e8-9ce2-eb00e9060128",
  "omny:clipId": "6573cdd3-d967-47af-a32f-ae32004b6df3",
  "pubDate": "Fri, 24 May 2019 09:00:00 +0000",
  "itunes:duration": 272,
  "enclosure": "",
  "link": "https://omny.fm/shows/brainstuff/how-many-legs-do-millipedes-have"
}