{
  "itunes:episodeType": "full",
  "itunes:title": "The Actual TOPGUN, Dave Berke, Reacts to \"TOPGUN: Maverick\" with Jocko",
  "title": "The Actual TOPGUN, Dave Berke, Reacts to \"TOPGUN: Maverick\" with Jocko",
  "itunes:author": "Jocko DEFCOR Network",
  "description": "<p>Reaction to the new movie \"TOPGUN: Maverick\" with Dave Berke and Jocko.</p><br/><br/>Support this podcast at — <a rel='payment' href='https://redcircle.com/jocko-podcast/exclusive-content'>https://redcircle.com/jocko-podcast/exclusive-content</a>",
  "content:encoded": "<p>Reaction to the new movie &#34;TOPGUN: Maverick&#34; with Dave Berke and Jocko.</p><br/><br/>Support this podcast at — <a rel='payment' href='https://redcircle.com/jocko-podcast/exclusive-content'>https://redcircle.com/jocko-podcast/exclusive-content</a>",
  "enclosure": "",
  "guid": "eb99caf3-8222-4d76-8927-f93ce081965b",
  "link": "http://jockopodcast.com",
  "pubDate": "Fri, 03 Jun 2022 07:00:00 &#43;0000",
  "itunes:image": "",
  "itunes:duration": 2248,
  "itunes:explicit": "no"
}