{
  "guid": "tag:soundcloud,2010:tracks/330164135",
  "title": "What next for the NHS and social care?",
  "pubDate": "Mon, 26 Jun 2017 00:00:00 +0000",
  "link": "https://soundcloud.com/weeklyeconomicspodcast/what-next-for-the-nhs-and-social-care",
  "itunes:duration": "00:30:31",
  "itunes:author": "New Economics Foundation",
  "itunes:explicit": "no",
  "itunes:summary": "6 out of 10 of us now think the NHS is one of the biggest issues facing Britain - the highest level of concern for 15 years.\n\nThis week we're joined by Allyson Pollock, Director of the Institute of Health and Society at Newcastle University, Sarah Lyall, Social Policy Lead at the New Economics Foundation and James Shield, who (when he's not producing the Weekly Economics Podcast) is Senior Policy Analyst at Macmillan Cancer Support to discuss the NHS, Social Care and more.  \n\n—\n\nEnjoying the show? Tweet us your comments and questions @NEF!\n\n—\n\nProduced by James Shield. Programme editor for the New Economics Foundation is Huw Jordan.\n\nThe award-winning Weekly Economics Podcast is brought to you by the New Economics Foundation – the UK's only people powered think tank. Find out more at www.neweconomics.org.",
  "itunes:subtitle": "6 out of 10 of us now think the NHS is one of the…",
  "description": "6 out of 10 of us now think the NHS is one of the biggest issues facing Britain - the highest level of concern for 15 years.\n\nThis week we're joined by Allyson Pollock, Director of the Institute of Health and Society at Newcastle University, Sarah Lyall, Social Policy Lead at the New Economics Foundation and James Shield, who (when he's not producing the Weekly Economics Podcast) is Senior Policy Analyst at Macmillan Cancer Support to discuss the NHS, Social Care and more.  \n\n—\n\nEnjoying the show? Tweet us your comments and questions @NEF!\n\n—\n\nProduced by James Shield. Programme editor for the New Economics Foundation is Huw Jordan.\n\nThe award-winning Weekly Economics Podcast is brought to you by the New Economics Foundation – the UK's only people powered think tank. Find out more at www.neweconomics.org.",
  "enclosure": "",
  "itunes:image": ""
}