{
  "title": "Open space invites opportunity",
  "itunes:title": "Open space invites opportunity",
  "description": "<p>Good ideas and connections come when time isn't rushed</p><p> </p> Learn more about your ad-choices at <a href=\"https://www.iheartpodcastnetwork.com\">https://www.iheartpodcastnetwork.com</a><p>See <a href=\"https://omnystudio.com/listener\">omnystudio.com/listener</a> for privacy information.</p>",
  "content:encoded": "<p>Good ideas and connections come when time isn't rushed</p><p> </p> Learn more about your ad-choices at <a href=\"https://www.iheartpodcastnetwork.com\">https://www.iheartpodcastnetwork.com</a><p>See <a href=\"https://omnystudio.com/listener\">omnystudio.com/listener</a> for privacy information.</p>",
  "itunes:summary": "Good ideas and connections come when time isn't rushed",
  "itunes:episodeType": "full",
  "itunes:author": "iHeartPodcasts",
  "itunes:image": "",
  "media:content": [
    {
      "media:player": ""
    },
    ""
  ],
  "guid": "ad51576a-d18a-11eb-993b-6be70bf4d991",
  "omny:clipId": "d3d7b9b0-a395-438e-9670-ae2d014e7502",
  "pubDate": "Fri, 06 Aug 2021 04:00:00 +0000",
  "itunes:duration": 361,
  "enclosure": "",
  "link": "https://omny.fm/shows/before-breakfast/open-space-invites-opportunity"
}