{
  "title": "228 - Boston Busing 1974",
  "itunes:title": "228 - Boston Busing 1974",
  "description": "<p>Comedians Dave Anthony and Gareth Reynolds examine the Boston busing riots of 1974. </p><p><a href=\"https://the-dollop-sources.squarespace.com/221240\" target=\"_blank\">SOURCES&nbsp;</a></p><p><a href=\"https://www.dolloppodcast.com/tour\" target=\"_blank\">TOUR DATES</a></p><p><a href=\"https://www.redbubble.com/people/mrfoz/collections/439251-the-dollop\" target=\"_blank\"> REDBUBBLE MERCH</a>&nbsp;</p>",
  "content:encoded": "<p>Comedians Dave Anthony and Gareth Reynolds examine the Boston busing riots of 1974. </p><p><a href=\"https://the-dollop-sources.squarespace.com/221240\" target=\"_blank\">SOURCES&nbsp;</a></p><p><a href=\"https://www.dolloppodcast.com/tour\" target=\"_blank\">TOUR DATES</a></p><p><a href=\"https://www.redbubble.com/people/mrfoz/collections/439251-the-dollop\" target=\"_blank\"> REDBUBBLE MERCH</a>&nbsp;</p>",
  "category": [
    "rocks",
    "the dollop",
    "south",
    "boston",
    "white",
    "louise",
    "southie",
    "judge",
    "Dave Anthony",
    "day",
    "mayor",
    "kelly",
    "park",
    "garrity",
    "dollop",
    "history",
    "gareth reynolds",
    "hicks",
    "riot",
    "american",
    "jose",
    "charlestown",
    "busing",
    "naacp",
    "hyde",
    "landsmark",
    "flag",
    "podcast"
  ],
  "itunes:keywords": "rocks, the dollop, south, boston, white, louise, southie, judge, Dave Anthony, day, mayor, kelly, park, garrity, dollop, history, gareth reynolds, hicks, riot, american, jose, charlestown, busing, naacp, hyde, landsmark, flag, podcast",
  "itunes:episodeType": "full",
  "itunes:author": "All Things Comedy",
  "itunes:image": "",
  "media:content": [
    {
      "media:player": ""
    },
    ""
  ],
  "guid": "adb9320d14121c74a44afcaa30b28952",
  "omny:clipId": "6834ae88-cfa5-4ca4-9ae4-ae24005c4563",
  "pubDate": "Mon, 19 Dec 2016 08:29:10 +0000",
  "itunes:duration": 4044,
  "enclosure": "",
  "link": "https://omny.fm/shows/the-dollop-with-dave-anthony-and-gareth-reynolds/228-boston-busing-1974",
  "itunes:explicit": "yes"
}