{
  "title": "Pride and Prejudice, Chapter 46",
  "description": "<p>Jane's letters finally arrive at Lambton, and Lizzy is in for a shock - Lydia has run off with Mr. Wickham! And Mr. Darcy arrived just in time to learn all about it. So much for seeing him again. Emotions are high, but Lizzy and the Gardiners make it to the carriage and are on the way back to Longbourn. Let their journey help you on your own journey into restful and relaxing slumber.&nbsp;</p>\n<p>-----</p>\n<p>Welcome to the Jane Austen Bedtime Stories podcast! Each episode is a section of a classic Jane Austen novel, read in soothing tones and set to calming music to help you fall asleep.</p>\n<p>With everything that is going on in the world, we find comfort in the familiar. For so many of us, Jane Austen's works are like a warm hug. So snuggle up under the covers and let the comforting words of Jane Austen lull you into sleep.</p>\n<p>-----</p>\n<p>Music [\"Reverie\"] by Scott Buckley – www.scottbuckley.com.au</p>\n<p><br></p>\n\n--- \n\nSupport this podcast: <a href=\"https://anchor.fm/jabedtimepod/support\" rel=\"payment\">https://anchor.fm/jabedtimepod/support</a>",
  "link": "https://anchor.fm/jabedtimepod/episodes/Pride-and-Prejudice--Chapter-46-e1jtrdi",
  "guid": "b369dde0-5994-41c8-a960-2bbd41cc8c6d",
  "dc:creator": "Jane Austen Bedtime Pod",
  "pubDate": "Tue, 14 Jun 2022 03:23:12 GMT",
  "enclosure": "",
  "itunes:summary": "<p>Jane's letters finally arrive at Lambton, and Lizzy is in for a shock - Lydia has run off with Mr. Wickham! And Mr. Darcy arrived just in time to learn all about it. So much for seeing him again. Emotions are high, but Lizzy and the Gardiners make it to the carriage and are on the way back to Longbourn. Let their journey help you on your own journey into restful and relaxing slumber.&nbsp;</p>\n<p>-----</p>\n<p>Welcome to the Jane Austen Bedtime Stories podcast! Each episode is a section of a classic Jane Austen novel, read in soothing tones and set to calming music to help you fall asleep.</p>\n<p>With everything that is going on in the world, we find comfort in the familiar. For so many of us, Jane Austen's works are like a warm hug. So snuggle up under the covers and let the comforting words of Jane Austen lull you into sleep.</p>\n<p>-----</p>\n<p>Music [\"Reverie\"] by Scott Buckley – www.scottbuckley.com.au</p>\n<p><br></p>\n\n--- \n\nSupport this podcast: <a href=\"https://anchor.fm/jabedtimepod/support\" rel=\"payment\">https://anchor.fm/jabedtimepod/support</a>",
  "itunes:explicit": "No",
  "itunes:duration": "00:45:30",
  "itunes:image": "",
  "itunes:season": 1,
  "itunes:episode": 28,
  "itunes:episodeType": "full"
}