{
  "title": "The Podcast Patent Problem",
  "itunes:title": "The Podcast Patent Problem",
  "description": "<p>How did a patent filed in 1996 cause huge headaches in the podcasting industry? And how did a decision in 2018 finally put the matter to rest? We look at the case of Personal Audio LLC versus podcasting.</p><p> </p> Learn more about your ad-choices at <a href=\"https://www.iheartpodcastnetwork.com\">https://www.iheartpodcastnetwork.com</a><p>See <a href=\"https://omnystudio.com/listener\">omnystudio.com/listener</a> for privacy information.</p>",
  "content:encoded": "<p>How did a patent filed in 1996 cause huge headaches in the podcasting industry? And how did a decision in 2018 finally put the matter to rest? We look at the case of Personal Audio LLC versus podcasting.</p><p> </p> Learn more about your ad-choices at <a href=\"https://www.iheartpodcastnetwork.com\">https://www.iheartpodcastnetwork.com</a><p>See <a href=\"https://omnystudio.com/listener\">omnystudio.com/listener</a> for privacy information.</p>",
  "itunes:episodeType": "full",
  "itunes:author": "iHeartPodcasts",
  "itunes:image": "",
  "media:content": [
    {
      "media:player": ""
    },
    ""
  ],
  "guid": "00994c6c-53b6-11e8-aa48-7361a07664ed",
  "omny:clipId": "3b649b7d-ced5-433a-9b79-ae2b0085f88f",
  "pubDate": "Wed, 03 Oct 2018 10:00:00 +0000",
  "itunes:duration": 1954,
  "enclosure": "",
  "link": "https://omny.fm/shows/techstuff/the-podcast-patent-problem"
}