{
  "id": "yt:video:pCgmnL_CZ4c",
  "yt:videoId": "pCgmnL_CZ4c",
  "yt:channelId": "UCLm6Qf523lkZ031DXClRKKA",
  "title": "Lab Skills: Measuring the size of a DNA fragment",
  "link": "",
  "author": {
    "name": "It's Learnable",
    "uri": "https://www.youtube.com/channel/UCLm6Qf523lkZ031DXClRKKA"
  },
  "published": "2021-09-02T21:00:16+00:00",
  "updated": "2022-08-19T15:50:13+00:00",
  "media:group": {
    "media:title": "Lab Skills: Measuring the size of a DNA fragment",
    "media:content": "",
    "media:thumbnail": "",
    "media:description": "You can use your gel to guess at the size of your DNA, or you can actually measure it. This video shows you how to do it right.",
    "media:community": {
      "media:starRating": "",
      "media:statistics": ""
    }
  }
}