{
  "title": "Patterns of lines emerging from looking at a cubic lattice of...",
  "description": "<img src=\"https://64.media.tumblr.com/b03130fadd650b894c6e4402054b5cad/tumblr_o7iibiZTOZ1qfg7o3o1_400.gifv\"/><br/><br/><p>Patterns of lines emerging from looking at a cubic lattice of points. The black lines form along directions in the cube where the eye can see unobstructed to the other side. [<a href=\"http://pastebin.com/vPEHvSSM\" target=\"_blank\">code</a>]</p>",
  "link": "https://blog.matthen.com/post/144687963121",
  "guid": "https://blog.matthen.com/post/144687963121",
  "pubDate": "Sat, 21 May 2016 06:41:13 +0100",
  "category": [
    "math",
    "science",
    "gif",
    "cube",
    "geometry",
    "animation"
  ]
}