{
  "title": "Bloomberg Businessweek Weekend-December 5, 2020",
  "itunes:title": "Bloomberg Businessweek Weekend-December 5, 2020",
  "description": "<p>Featuring some of our favorite conversations from the Bloomberg 50.</p><p>Hosted by Carol Massar. Producer: Doni Holloway.</p><p>Hear the show live at 2PM ET on WBBR 1130 AM New York, Bloomberg 106.1 FM Boston, Bloomberg 960 AM San Francisco, WDCH 99.1 FM in Washington D.C. Metro, Sirius/XM channel 119, on the Bloomberg Business App, Radio.com, the iHeartRadio app and at Bloomberg.com/audio.</p><p>You can also watch Bloomberg Businessweek on YouTube - just search for Bloomberg Global News. Like us at Bloomberg Radio on Facebook and follow us on Twitter @carolmassar and @BW</p><p>See <a href=\"https://omnystudio.com/listener\">omnystudio.com/listener</a> for privacy information.</p>",
  "content:encoded": "<p>Featuring some of our favorite conversations from the Bloomberg 50.</p><p>Hosted by Carol Massar. Producer: Doni Holloway.</p><p>Hear the show live at 2PM ET on WBBR 1130 AM New York, Bloomberg 106.1 FM Boston, Bloomberg 960 AM San Francisco, WDCH 99.1 FM in Washington D.C. Metro, Sirius/XM channel 119, on the Bloomberg Business App, Radio.com, the iHeartRadio app and at Bloomberg.com/audio.</p><p>You can also watch Bloomberg Businessweek on YouTube - just search for Bloomberg Global News. Like us at Bloomberg Radio on Facebook and follow us on Twitter @carolmassar and @BW</p><p>See <a href=\"https://omnystudio.com/listener\">omnystudio.com/listener</a> for privacy information.</p>",
  "itunes:episodeType": "full",
  "itunes:author": "Bloomberg",
  "itunes:image": "",
  "media:content": [
    {
      "media:player": ""
    },
    ""
  ],
  "guid": "8b6a480c-38a4-11eb-89f6-775f93bc0135",
  "omny:clipId": "16b96722-4357-4705-8647-ae2b004f12d7",
  "pubDate": "Mon, 07 Dec 2020 16:03:29 +0000",
  "itunes:duration": 3870,
  "enclosure": "",
  "link": "https://omny.fm/shows/bloomberg-businessweek/bloomberg-businessweek-weekend-december-5-2020"
}