{
  "guid": "CDOC-116hdoc127",
  "title": "H. Doc. 116-127 - CONTINUATION OF THE NATIONAL EMERGENCY WITH RESPECT TO THE ACTIONS OF THE GOVERNMENT OF SYRIA",
  "pubDate": "Fri, 08 May 2020 00:00:00 +0000",
  "category": "Congressional Committee Materials",
  "link": "https://www.govinfo.gov/app/details/CDOC-116hdoc127",
  "description": "<h2>Metadata download</h2>\n <a href=\"https://www.govinfo.gov/metadata/pkg/CDOC-116hdoc127/mods.xml\">Descriptive Metadata (MODS)</a><br/>\n <a href=\"https://www.govinfo.gov/metadata/pkg/CDOC-116hdoc127/premis.xml\">Preservation Metadata (PREMIS)</a><br/>\n <h2>All Content and Metadata files, including granules</h2> <a href=\"https://www.govinfo.gov/content/pkg/CDOC-116hdoc127.zip\">ZIP</a>"
}