{
  "title": "Dave Puts the Fun in Funeral",
  "description": "The Sequel Game, Christmas Wish, Radio Pictionary, War of the Roses, Throwback Threesome, Mixtape Game, and more!",
  "itunes:summary": "The Sequel Game, Christmas Wish, Radio Pictionary, War of the Roses, Throwback Threesome, Mixtape Game, and more!",
  "itunes:subtitle": "The Sequel Game, Christmas Wish, Radio Pictionary, War of the Roses, Throwback Threesome, Mixtape Game, and more!",
  "itunes:author": "101.3 KDWB",
  "itunes:image": "",
  "link": "https://www.iheart.com/podcast/139-the-dave-ryan-show-26584068/",
  "guid": "https://dts.podtrac.com/redirect.m4a/post.futurimedia.com/kdwb/playlist/2/670.m4a",
  "enclosure": "",
  "itunes:explicit": "clean",
  "pubDate": "Thu, 06 Dec 2018 10:04:03 -0600",
  "itunes:duration": "00:00:00"
}