{
  "title": "Trend, Oregon 3/18: PS5, Amanda Bynes, China Virus, Utah Earthquake, Defense Production Act",
  "itunes:title": "Trend, Oregon 3/18: PS5, Amanda Bynes, China Virus, Utah Earthquake, Defense Production Act",
  "description": "<p>On this edition of Trend, Oregon Jack and Miles discuss Sony revealing some stats about the PS5, Amanda Bynes is pregnant, more people in charge are using racist language to describe COVID-19, there was a 5.7 earthquake in Utah, and the White House is getting medical equipment out there as fast as possible.</p><p> </p> Learn more about your ad-choices at <a href=\"https://www.iheartpodcastnetwork.com\">https://www.iheartpodcastnetwork.com</a><p>See <a href=\"https://omnystudio.com/listener\">omnystudio.com/listener</a> for privacy information.</p>",
  "content:encoded": "<p>On this edition of Trend, Oregon Jack and Miles discuss Sony revealing some stats about the PS5, Amanda Bynes is pregnant, more people in charge are using racist language to describe COVID-19, there was a 5.7 earthquake in Utah, and the White House is getting medical equipment out there as fast as possible.</p><p> </p> Learn more about your ad-choices at <a href=\"https://www.iheartpodcastnetwork.com\">https://www.iheartpodcastnetwork.com</a><p>See <a href=\"https://omnystudio.com/listener\">omnystudio.com/listener</a> for privacy information.</p>",
  "itunes:episodeType": "full",
  "itunes:author": "iHeartPodcasts",
  "itunes:image": "",
  "media:content": [
    {
      "media:player": ""
    },
    ""
  ],
  "guid": "89eafec6-6943-11ea-8a6a-87660e5eb338",
  "omny:clipId": "827e3173-f264-499b-9d18-ae2b009b334c",
  "pubDate": "Wed, 18 Mar 2020 23:00:49 +0000",
  "itunes:duration": 712,
  "enclosure": "",
  "link": "https://omny.fm/shows/the-daily-zeitgeist/trend-oregon-3-18-ps5-amanda-bynes-china-virus-uta"
}