{
  "guid": "2807a4c300d811cbba6e65e5d784a7df",
  "title": "The God Problem",
  "description": "<p>Kevin Allison shares two faith-shaking stories about grappling with angels and demons in his very Catholic youth.</p><p>Support RISK! on Patreon at <a href=\"Patreon.com/RISK\">Patreon.com/RISK</a></p><p>Make a one-time donation to RISK! at <a href=\"PayPal.me/RISKshow\">PayPal.me/RISKshow</a></p><p>Get tickets to RISK! live shows at <a href=\"https://www.risk-show.com/tour/\">RISK-show.com/tour</a></p><p>Get the RISK! book at <a href=\"TheRISKBook.com\">TheRISKBook.com</a></p><p>Take our storytelling classes at <a href=\"TheStoryStudio.org\">TheStoryStudio.org</a></p><p>Hire Kevin Allison to make a personalized video at <a href=\"Cameo.com/TheKevinAllison\">Cameo.com/TheKevinAllison</a></p><p>Hire Kevin Allison as a coach at <a href=\"KevinAllison.com\">KevinAllison.com</a></p>\n",
  "pubDate": "Sat, 4 Jul 2015 17:00:00 +0000",
  "author": "Kevin@RISK-show.com (LeeDM101, Kevin Allison, Ramona Falls)",
  "link": "https://www.risk-show.com/podcast/the-god-problem/",
  "content:encoded": "<p>Kevin Allison shares two faith-shaking stories about grappling with angels and demons in his very Catholic youth.</p><p>Support RISK! on Patreon at <a href=\"Patreon.com/RISK\">Patreon.com/RISK</a></p><p>Make a one-time donation to RISK! at <a href=\"PayPal.me/RISKshow\">PayPal.me/RISKshow</a></p><p>Get tickets to RISK! live shows at <a href=\"https://www.risk-show.com/tour/\">RISK-show.com/tour</a></p><p>Get the RISK! book at <a href=\"TheRISKBook.com\">TheRISKBook.com</a></p><p>Take our storytelling classes at <a href=\"TheStoryStudio.org\">TheStoryStudio.org</a></p><p>Hire Kevin Allison to make a personalized video at <a href=\"Cameo.com/TheKevinAllison\">Cameo.com/TheKevinAllison</a></p><p>Hire Kevin Allison as a coach at <a href=\"KevinAllison.com\">KevinAllison.com</a></p>\n",
  "enclosure": "",
  "itunes:title": "The God Problem",
  "itunes:author": "LeeDM101, Kevin Allison, Ramona Falls",
  "itunes:image": "",
  "itunes:duration": "00:44:12",
  "itunes:summary": "Kevin Allison shares two faith-shaking stories about grappling with angels and demons in his very Catholic youth.",
  "itunes:subtitle": "Kevin Allison shares two faith-shaking stories about grappling with angels and demons in his very Catholic youth.",
  "itunes:keywords": "storytelling podcasts",
  "itunes:explicit": "yes",
  "itunes:episodeType": "full",
  "itunes:season": 4
}