{
  "title": "347 - NY Policeman's Riot w/Dave Hill (Live in NY)",
  "itunes:title": "347 - NY Policeman's Riot w/Dave Hill (Live in NY)",
  "description": "Comedians Dave Anthony and Gareth Reynolds are joined by Dave Hill to examine the  New York City Policeman's riot.   SOURCES  OFFICIAL MERCH TOUR DATES",
  "content:encoded": "Comedians Dave Anthony and Gareth Reynolds are joined by Dave Hill to examine the  New York City Policeman's riot.   SOURCES  OFFICIAL MERCH TOUR DATES",
  "category": [
    "the dollop",
    "Dave Anthony",
    "dollop",
    "history",
    "gareth reynolds",
    "jose",
    "podcast"
  ],
  "itunes:keywords": "the dollop, Dave Anthony, dollop, history, gareth reynolds, jose, podcast",
  "itunes:episodeType": "full",
  "itunes:author": "All Things Comedy",
  "itunes:image": "",
  "media:content": [
    {
      "media:player": ""
    },
    ""
  ],
  "guid": "2b5d67f70ce94491833f48d9b9529310",
  "omny:clipId": "21bff999-e546-44d6-a4af-ae24004d6e3e",
  "pubDate": "Tue, 09 Oct 2018 19:10:15 +0000",
  "itunes:duration": 4657,
  "enclosure": "",
  "link": "https://omny.fm/shows/the-dollop-with-dave-anthony-and-gareth-reynolds/347-ny-policemans-riot-w-dave-hill-live-in-ny",
  "itunes:explicit": "yes"
}