{
  "title": "#030 - UNCLE JOEY'S JOINT",
  "pubDate": "Thu, 14 Jan 2021 12:00:00 +0000",
  "guid": "3c794072-8639-4584-b5a6-601a8d43c548",
  "link": "https://thechurchofwhatshappeningnow.libsyn.com/030-uncle-joeys-joint",
  "itunes:image": "",
  "description": "<p class=\"p1\"><span class=\"s1\">Welcome to Uncle Joey's Joint....</span></p> <p class=\"p1\"><span class=\"s1\">Today, we talk about forgiveness.</span></p> <p class=\"p1\"><span class=\"s1\">This episode is brought to you DraftKings, Blue Chew & Stamps.com......</span></p> <p class=\"p1\"><span class=\"s1\">Go to <a href= \"https://www.draftkings.com\">https://www.draftkings.com</a></span> <span class=\"s1\">and enter Code: JOEY</span></p> <p class=\"p1\"><span class=\"s1\">Go to <a href= \"https://www.bluechew.com\">https://www.bluechew.com</a></span> <span class=\"s1\">and enter Code: JOEY</span></p> <p class=\"p1\"><span class=\"s1\">Go to <a href= \"https://www.stamps.com\">https://www.stamps.com</a></span> <span class=\"s1\">and enter Code: JOEY</span></p> <p class=\"p1\"><span class=\"s1\">And don’t forget.....</span></p> <p class=\"p1\"><span class=\"s1\">The Mind Of Joey Diaz is on PATREON:</span></p> <p class=\"p1\"><span class=\"s1\"><a href= \"https://www.patreon.com/joeydiaz\">https://www.patreon.com/joeydiaz</a></span></p> <p class=\"p1\"><span class=\"s1\">#JoeyDiaz #Madflavor #UncleJoeysJoint</span></p>",
  "content:encoded": "<p class=\"p1\">Welcome to Uncle Joey's Joint....</p> <p class=\"p1\">Today, we talk about forgiveness.</p> <p class=\"p1\">This episode is brought to you DraftKings, Blue Chew & Stamps.com......</p> <p class=\"p1\">Go to <a href= \"https://www.draftkings.com\">https://www.draftkings.com</a> and enter Code: JOEY</p> <p class=\"p1\">Go to <a href= \"https://www.bluechew.com\">https://www.bluechew.com</a> and enter Code: JOEY</p> <p class=\"p1\">Go to <a href= \"https://www.stamps.com\">https://www.stamps.com</a> and enter Code: JOEY</p> <p class=\"p1\">And don’t forget.....</p> <p class=\"p1\">The Mind Of Joey Diaz is on PATREON:</p> <p class=\"p1\"><a href= \"https://www.patreon.com/joeydiaz\">https://www.patreon.com/joeydiaz</a></p> <p class=\"p1\">#JoeyDiaz #Madflavor #UncleJoeysJoint</p>",
  "enclosure": "",
  "itunes:duration": "01:03:07",
  "itunes:explicit": true,
  "itunes:keywords": "",
  "itunes:subtitle": "Welcome to Uncle Joey's Joint.... Today, we talk about forgiveness. This episode is brought to you DraftKings, Blue Chew & Stamps.com...... Go to  and enter Code: JOEY Go to  and enter Code: JOEY Go to  and enter Code: JOEY And don’t forget........",
  "itunes:episodeType": "full"
}