{
  "title": "78: Upheaval (آشوب)",
  "itunes:title": "خلاصه کتاب آشوب",
  "pubDate": "Wed, 25 May 2022 12:22:07 +0000",
  "guid": "9cb0955f-6324-4508-85d0-3ec5e2bb211a",
  "link": "https://bplus.libsyn.com/episode-78",
  "itunes:image": "",
  "description": "<p style=\"text-align: right;\"><span style= \"font-weight: 400;\">نویسنده‌</span><strong>:</strong> <a href= \"http://www.jareddiamond.org/Jared_Diamond/Welcome.html\"><span style=\"font-weight: 400;\"> جرد دایموند</span></a></p> <p style=\"text-align: right;\"><span style=\"font-weight: 400;\">متن: عباس سیدین | روایت: علی بندری</span></p> <p style=\"text-align: right;\"><span style= \"font-weight: 400;\"> تدوین: نیما خالدی‌کیا، امید صدیق‌فر  </span></p> <p style=\"text-align: right;\"><span style= \"font-weight: 400;\">موسیقی تیتراژ</span> <strong>:</strong> <a href=\"https://www.instagram.com/peyman.arabzadeh.official/?igshid=1dskr5qet0bng\"> <span style=\"font-weight: 400;\">پیمان عرب‌زاده</span></a> <span style=\"font-weight: 400;\">| </span></p> <p style=\"text-align: right;\"><span style= \"font-weight: 400;\">موسیقی متن: Patrick Patrikios| Kevin MacLeod | Quincas Moreira</span></p> <p style=\"text-align: right;\"><a href= \"https://bpluspodcast.com/blog\"><span style= \"font-weight: 400;\">وبلاگ بی‌پلاس</span></a></p> <p style=\"text-align: right;\"><a href= \"https://www.youtube.com/channel/UChWB95_-n9rUc3H9srsn9bQ?pbjreload=101\"> <span style=\"font-weight: 400;\">یوتیوب بی‌پلاس </span></a></p> <p style=\"text-align: right;\"><span style= \"font-weight: 400;\">      کتاب‌های بی‌پلاس را از</span> <a href= \"https://bpluspodcast.com/where-to-buy/\"><span style= \"font-weight: 400;\">اینجا</span></a><span style= \"font-weight: 400;\">  بخرید.</span></p> <p style=\"text-align: right;\"><span style= \"font-weight: 400;\">       </span><a href=\"https://bpluspodcast.com/support/\"><span style=\"font-weight: 400;\">پشتیبانی از بی‌پلاس</span></a></p> <p style=\"text-align: right;\"><span style=\"font-weight: 400;\">با تشکر از اسپانسرهای این اپیزود: </span></p> <p style=\"text-align: right;\"><a href= \"http://didar.me\"><span style=\"font-weight: 400;\">سی آر‌ام دیدار</span></a></p> <p style=\"text-align: right;\"><a href= \"https://fidibo.com/landings/fidiplus/?utm_source=podcast&utm_medium=social-paid&utm_campaign=fidiplus&utm_term=bplus\"> <span style=\"font-weight: 400;\">اشتراک فیدی‌پلاس</span></a></p> <p style=\"text-align: right;\"><span style=\"font-weight: 400;\">عضویت در</span> <a href= \"https://bpluspodcast.com/newsletter/\"><span style= \"font-weight: 400;\">خبرنامه‌ی بی‌پلاس</span></a></p>",
  "content:encoded": "<p style=\"text-align: right;\">نویسنده‌: <a href= \"http://www.jareddiamond.org/Jared_Diamond/Welcome.html\"> جرد دایموند</a></p> <p style=\"text-align: right;\">متن: عباس سیدین | روایت: علی بندری</p> <p style=\"text-align: right;\"> تدوین: نیما خالدی‌کیا، امید صدیق‌فر  </p> <p style=\"text-align: right;\">موسیقی تیتراژ : <a href=\"https://www.instagram.com/peyman.arabzadeh.official/?igshid=1dskr5qet0bng\"> پیمان عرب‌زاده</a> | </p> <p style=\"text-align: right;\">موسیقی متن: Patrick Patrikios| Kevin MacLeod | Quincas Moreira</p> <p style=\"text-align: right;\"><a href= \"https://bpluspodcast.com/blog\">وبلاگ بی‌پلاس</a></p> <p style=\"text-align: right;\"><a href= \"https://www.youtube.com/channel/UChWB95_-n9rUc3H9srsn9bQ?pbjreload=101\"> یوتیوب بی‌پلاس </a></p> <p style=\"text-align: right;\">      کتاب‌های بی‌پلاس را از <a href= \"https://bpluspodcast.com/where-to-buy/\">اینجا</a>  بخرید.</p> <p style=\"text-align: right;\">       <a href=\"https://bpluspodcast.com/support/\">پشتیبانی از بی‌پلاس</a></p> <p style=\"text-align: right;\">با تشکر از اسپانسرهای این اپیزود: </p> <p style=\"text-align: right;\"><a href= \"http://didar.me\">سی آر‌ام دیدار</a></p> <p style=\"text-align: right;\"><a href= \"https://fidibo.com/landings/fidiplus/?utm_source=podcast&utm_medium=social-paid&utm_campaign=fidiplus&utm_term=bplus\"> اشتراک فیدی‌پلاس</a></p> <p style=\"text-align: right;\">عضویت در <a href= \"https://bpluspodcast.com/newsletter/\">خبرنامه‌ی بی‌پلاس</a></p>",
  "enclosure": "",
  "itunes:duration": "01:19:02",
  "itunes:explicit": false,
  "itunes:keywords": "persian,alibandari",
  "itunes:subtitle": "کشورها چطور از پس بحران‌های عظیم بر می‌آیند؟",
  "itunes:season": 5,
  "itunes:episode": 78,
  "itunes:episodeType": "full",
  "itunes:author": "Ali Bandari"
}