{
  "title": "The cost of voting in a pandemic",
  "itunes:title": "The cost of voting in a pandemic",
  "description": "<p>Welcome to Apple News Today, a new show from Apple News. In today's episode:</p><p><a href=\"https://apple.news/AEJE3GM49RDOGUEFwaflmPw?campaign_id=applenewstoday_shownotes\"><i>USA Today</i> and Columbia Journalism Investigations</a> look at how states and counties are running short on funds to hold elections. </p><p>The city of Asheville, North Carolina, takes a step toward reparations. <a href=\"https://apple.news/AykHpcaf4RxyEvdWwJlxmHw?campaign_id=applenewstoday_shownotes\"><i>The News & Observer</i></a> has the story. And <a href=\"https://apple.news/A9BqxnpfJRYSHeHdY0aJnvA?campaign_id=applenewstoday_shownotes\"><i>Business Insider</i></a> tracks how reparations are perceived on a national scale. </p><p>According to <a href=\"https://apple.news/AfG9gfn8OQ7GRDmB-iDgO7w?campaign_id=applenewstoday_shownotes\"><i>Scientific American</i></a>, humans aren’t the only animals who practice social distancing.</p><p>And <a href=\"https://apple.news/AYZt0N06_RDiYKtvmnxVWFA?campaign_id=applenewstoday_shownotes\"><i>Condé Nast Traveler</i></a> says Iceland is giving us all permission to scream.</p><br>",
  "content:encoded": "<p>Welcome to Apple News Today, a new show from Apple News. In today's episode:</p><p><a href=\"https://apple.news/AEJE3GM49RDOGUEFwaflmPw?campaign_id=applenewstoday_shownotes\"><i>USA Today</i> and Columbia Journalism Investigations</a> look at how states and counties are running short on funds to hold elections. </p><p>The city of Asheville, North Carolina, takes a step toward reparations. <a href=\"https://apple.news/AykHpcaf4RxyEvdWwJlxmHw?campaign_id=applenewstoday_shownotes\"><i>The News & Observer</i></a> has the story. And <a href=\"https://apple.news/A9BqxnpfJRYSHeHdY0aJnvA?campaign_id=applenewstoday_shownotes\"><i>Business Insider</i></a> tracks how reparations are perceived on a national scale. </p><p>According to <a href=\"https://apple.news/AfG9gfn8OQ7GRDmB-iDgO7w?campaign_id=applenewstoday_shownotes\"><i>Scientific American</i></a>, humans aren’t the only animals who practice social distancing.</p><p>And <a href=\"https://apple.news/AYZt0N06_RDiYKtvmnxVWFA?campaign_id=applenewstoday_shownotes\"><i>Condé Nast Traveler</i></a> says Iceland is giving us all permission to scream.</p><br>",
  "enclosure": "",
  "guid": "58d6a217-c3a4-4e8a-806f-604a6190c386",
  "pubDate": "Thu, 16 Jul 2020 10:57:58 GMT",
  "link": "https://apple.news/AmFh1ejwQT9Oti2TCeV7yxQ",
  "itunes:episodeType": "full",
  "itunes:duration": 465,
  "itunes:explicit": false,
  "media:restriction": "us uk ca au de se fr jp no dk kr es nl br ie mx sa nz"
}