{
  "title": "Blocked Shots with Alex Berenson and Russ Vought",
  "itunes:title": "Blocked Shots with Alex Berenson and Russ Vought",
  "description": "<p>Parents have overwhelmingly rejected Covid vaccines for their young children. Foreign countries are moving away from mass vaccination of the young. But in America, Biden's CDC is pushing for Covid shots to go on the child vaccine schedule. Alex Berenson joins Charlie to discuss how opposing mandates could be a GOP path to victory in blue states. Plus, Russ Vought joins to discuss the intel agencies' decades-long history of hurting ordinary Americans.</p><p><a href=\"http://www.charliekirk.com/support\" rel=\"payment\">Support the show: http://www.charliekirk.com/support</a></p><p>See <a href=\"https://omnystudio.com/listener\">omnystudio.com/listener</a> for privacy information.</p>",
  "content:encoded": "<p>Parents have overwhelmingly rejected Covid vaccines for their young children. Foreign countries are moving away from mass vaccination of the young. But in America, Biden's CDC is pushing for Covid shots to go on the child vaccine schedule. Alex Berenson joins Charlie to discuss how opposing mandates could be a GOP path to victory in blue states. Plus, Russ Vought joins to discuss the intel agencies' decades-long history of hurting ordinary Americans.</p><p><a href=\"http://www.charliekirk.com/support\" rel=\"payment\">Support the show: http://www.charliekirk.com/support</a></p><p>See <a href=\"https://omnystudio.com/listener\">omnystudio.com/listener</a> for privacy information.</p>",
  "itunes:episodeType": "full",
  "itunes:author": "Charlie Kirk",
  "itunes:image": "",
  "media:content": [
    {
      "media:player": ""
    },
    ""
  ],
  "guid": "13f6a43c-7399-4ac3-a0ba-af34000e00fb",
  "omny:clipId": "13f6a43c-7399-4ac3-a0ba-af34000e00fb",
  "pubDate": "Thu, 20 Oct 2022 00:51:51 +0000",
  "itunes:duration": 1886,
  "enclosure": "",
  "link": "https://omny.fm/shows/the-charlie-kirk-show/blocked-shots-with-alex-berenson-and-russ-vought"
}