{
  "title": "Ep 207: Bonding, Chastity Belts & Needing Male Orgasms (Ft. Troy)",
  "itunes:title": "Ep 207: Bonding, Chastity Belts & Needing Male Orgasms (Ft. Troy)",
  "description": "<p>This week the duo is joined by Troy, the intimacy coordinator and co-writer of the Netflix hit show Bonding. This week we get into how sex and BDSM is portrayed on film and television. The ladies also hit up a friend to discuss why as women we are programmed to need the male nut. WHY? Orgasms are important on both ends apparently. For the WD we discuss the pricey side of sex toys and how kinky Troy’s collection gets. She references one item cost as much as $22,000! </p><p><br></p><p>Follow this week’s guest </p><p>Instagram @oliviatroy</p><p>Website Oliviatroy.com</p><p>Agency @reponset RepOnSet.com</p><p><br></p><p>Follow the hosts on social media Weezy @Weezywtf & Mandii @Fullcourtpumps and follow the Whoreible Decisions pages</p><p>Instagram @whoreible_decisions</p><p>Twitter @whoreiblepod</p><p><br></p><p>Don't forget to tag #whoreibledecisions or @ us to let us know what you think of this week's episode!</p><p><br></p><p>Want more? Bonus episodes, merch and more Whoreible Decisions!! Become a Patron at Patreon.com/whoreibledecisions</p><p><br></p><p>Want some Whoreible Decisions merchandise? GET YOURS NOW AT <a href=\"https://www.google.com/url?q=http://WHOREHIVE.COM&sa=D&source=editors&ust=1613965167864000&usg=AFQjCNFV72IL0wUPI26vX-1jrLTT8tGDMg\">WHOREHIVE.COM</a></p><p> </p> Learn more about your ad-choices at <a href=\"https://www.iheartpodcastnetwork.com\">https://www.iheartpodcastnetwork.com</a><p>See <a href=\"https://omnystudio.com/listener\">omnystudio.com/listener</a> for privacy information.</p>",
  "content:encoded": "<p>This week the duo is joined by Troy, the intimacy coordinator and co-writer of the Netflix hit show Bonding. This week we get into how sex and BDSM is portrayed on film and television. The ladies also hit up a friend to discuss why as women we are programmed to need the male nut. WHY? Orgasms are important on both ends apparently. For the WD we discuss the pricey side of sex toys and how kinky Troy’s collection gets. She references one item cost as much as $22,000! </p><p><br></p><p>Follow this week’s guest </p><p>Instagram @oliviatroy</p><p>Website Oliviatroy.com</p><p>Agency @reponset RepOnSet.com</p><p><br></p><p>Follow the hosts on social media Weezy @Weezywtf & Mandii @Fullcourtpumps and follow the Whoreible Decisions pages</p><p>Instagram @whoreible_decisions</p><p>Twitter @whoreiblepod</p><p><br></p><p>Don't forget to tag #whoreibledecisions or @ us to let us know what you think of this week's episode!</p><p><br></p><p>Want more? Bonus episodes, merch and more Whoreible Decisions!! Become a Patron at Patreon.com/whoreibledecisions</p><p><br></p><p>Want some Whoreible Decisions merchandise? GET YOURS NOW AT <a href=\"https://www.google.com/url?q=http://WHOREHIVE.COM&sa=D&source=editors&ust=1613965167864000&usg=AFQjCNFV72IL0wUPI26vX-1jrLTT8tGDMg\">WHOREHIVE.COM</a></p><p> </p> Learn more about your ad-choices at <a href=\"https://www.iheartpodcastnetwork.com\">https://www.iheartpodcastnetwork.com</a><p>See <a href=\"https://omnystudio.com/listener\">omnystudio.com/listener</a> for privacy information.</p>",
  "itunes:episodeType": "full",
  "itunes:author": "The Black Effect and iHeartPodcasts",
  "itunes:image": "",
  "media:content": [
    {
      "media:player": ""
    },
    ""
  ],
  "guid": "24cac9b6-72ef-11eb-853d-03655ad4ede6",
  "omny:clipId": "0a5b6760-c228-4eb3-bca6-ae33006df321",
  "pubDate": "Mon, 01 Mar 2021 05:29:19 +0000",
  "itunes:duration": 4156,
  "enclosure": "",
  "link": "https://omny.fm/shows/whoreible-decisions-1/ep-207-bonding-chastity-belts-needing-male-orgasms"
}